agent_mcp/__init__.py
agent_mcp/camel_mcp_adapter.py
agent_mcp/cli.py
agent_mcp/crewai_mcp_adapter.py
agent_mcp/enhanced_mcp_agent.py
agent_mcp/heterogeneous_group_chat.py
agent_mcp/langchain_mcp_adapter.py
agent_mcp/langgraph_mcp_adapter.py
agent_mcp/mcp_agent.py
agent_mcp/mcp_decorator.py
agent_mcp/mcp_langgraph.py
agent_mcp/mcp_transaction.py
agent_mcp/mcp_transport.py
agent_mcp/mcp_transport_enhanced.py
agent_mcp/proxy_agent.py
demos/__init__.py
demos/basic/__init__.py
demos/basic/framework_examples.py
demos/basic/langchain_camel_demo.py
demos/basic/simple_chat.py
demos/basic/simple_integration_example.py
demos/collaboration/collaborative_task_example.py
demos/collaboration/group_chat_example.py
demos/collaboration/simplified_crewai_example.py
demos/langgraph/autonomous_langgraph_network.py
demos/langgraph/langgraph_agent_network.py
demos/langgraph/langgraph_collaborative_task.py
demos/langgraph/langgraph_example.py
demos/langgraph/run_langgraph_examples.py
demos/network/agent_network_example.py
demos/network/email_agent.py
demos/network/email_agent_demo.py
demos/network/heterogeneous_network_example.py
demos/network/multi_framework_example.py
demos/utils/check_imports.py
demos/workflows/autonomous_agent_workflow.py
demos/workflows/mcp_features_demo.py
demos/workflows/run_agent_collaboration_demo.py
demos/workflows/run_agent_collaboration_with_logs.py
demos/workflows/show_agent_interactions.py
demos/workflows/simplified_autonomous_demo.py
functions/main.py
functions/mcp_network_server.py
functions/utils.py
agent_mcp-0.1.4.dist-info/METADATA
agent_mcp-0.1.4.dist-info/WHEEL
agent_mcp-0.1.4.dist-info/entry_points.txt
agent_mcp-0.1.4.dist-info/top_level.txt
agent_mcp-0.1.4.dist-info/RECORD
