Metadata-Version: 2.4
Name: agent-mcp
Version: 0.1.4
Summary: A bridge agent to enable agents with Model Context Protocol capabilities to be added to a Multi-agent Collaboration Network (MCN) to run on a Multi-agent Collaboration Platform (MCP)
Home-page: https://github.com/grupa-ai/agent-mcp
Author: GrupaAI
License-Expression: MIT
Project-URL: Homepage, https://github.com/grupa-ai/agent-mcp
Project-URL: Documentation, https://github.com/grupa-ai/agent-mcp#readme
Project-URL: Repository, https://github.com/grupa-ai/agent-mcp
Classifier: Development Status :: 3 - Alpha
Classifier: Intended Audience :: Developers
Classifier: Operating System :: OS Independent
Classifier: Programming Language :: Python :: 3
Classifier: Programming Language :: Python :: 3.11
Classifier: Programming Language :: Python :: 3 :: Only
Requires-Python: >=3.11
Requires-Dist: autogen
Requires-Dist: langchain
Requires-Dist: langchain-openai
Requires-Dist: langchain-community
Requires-Dist: crewai>=0.11.0
Requires-Dist: langgraph>=0.0.15
Requires-Dist: openai>=1.12.0
Requires-Dist: fastapi==0.104.1
Requires-Dist: uvicorn==0.24.0
Requires-Dist: sse-starlette==1.8.2
Requires-Dist: firebase-admin==6.4.0
Requires-Dist: python-multipart==0.0.6
Requires-Dist: python-dotenv==1.0.0
Requires-Dist: google-cloud-firestore==2.13.1
Requires-Dist: aiohttp==3.9.1
Requires-Dist: duckduckgo-search==4.1.1
Dynamic: home-page
Dynamic: requires-python
